fake_httpd/__init__.py
fake_httpd/config.py
fake_httpd/main.py
fake_httpd/request.py
fake_httpd/version.py
fake_httpd/tests/__init__.py
fake_httpd/tests/test_config.py
fake_httpd/tests/test_request.py
fake_httpd-0.0.2rc11.dist-info/COPYING
fake_httpd-0.0.2rc11.dist-info/LICENSE
fake_httpd-0.0.2rc11.dist-info/METADATA
fake_httpd-0.0.2rc11.dist-info/WHEEL
fake_httpd-0.0.2rc11.dist-info/entry_points.txt
fake_httpd-0.0.2rc11.dist-info/top_level.txt
fake_httpd-0.0.2rc11.dist-info/RECORD
