Metadata-Version: 2.1
Name: fake-httpd
Version: 0.0.2rc11
Summary: Fake httpd which parses/logs requests
Home-page: https://github.com/mteofrancis/fake-httpd
Author: Francis M
Author-email: mteofrancis@gmail.com
License: UNKNOWN
Project-URL: Bug Tracker, https://github.com/mteofrancis/fake-httpd/issues
Platform: UNKNOWN
Classifier: Programming Language :: Python :: 3
Classifier: Development Status :: 3 - Alpha
Classifier: Topic :: Internet :: WWW/HTTP :: HTTP Servers
Classifier: License :: OSI Approved :: GNU General Public License v2 (GPLv2)
Requires-Python: >=3.8
License-File: LICENSE
License-File: COPYING
Requires-Dist: mteo-util (>=0.0.2)
